[
  {
    "hotel_id": "52027642",
    "hotel_url": "https://www.agoda.com/l7-haeundae/hotel/busan-kr.html",
    "name": "L7 HAEUNDAE by LOTTE HOTELS",
    "detail": "The rooftop pool at sunset was a highlight of my stay.",
    "area": "Haeundae-gu,Busan - View on map",
    "rating": "9",
    "reviews": "2691 reviews",
    "price": "172",
    "gallery": [
      "https://pix8.agoda.net/hotelImages/52027642/-1/3da89d0fb939eff557d32cf43c8ed6e4.jpg?ce=0&s=1024x768",
      "https://pix8.agoda.net/hotelImages/52027642/1077788977/cea323d78ca7967a6c92e426531e3222.jpg?ce=2&s=1024x768",
      "https://pix8.agoda.net/hotelImages/52027642/-1/fb4f3cd0393839d550a648de4c7b6598.jpg?ce=0&s=1024x768",
      "https://pix8.agoda.net/hotelImages/52027642/-1/787b24ad68ec5aba265af627edeee297.jpg?ce=0&s=1024x768",
      "https://pix8.agoda.net/hotelImages/52027642/-1/5dcba9f3dc9e05723b6c942327c3e95c.jpg?ce=0&s=1024x768",
      "https://pix8.agoda.net/hotelImages/52027642/-1/a1f24973ae9bc54160fc19db2f9528f1.jpg?ce=0&s=1024x768",
      "https://q-xx.bstatic.com/xdata/images/hotel/max1000/686908741.jpg?k=2260a8c3a3565b9a7c69720514840c86e18ca0248d0660404736520a1a862f8e&s=1024x768",
      "https://pix8.agoda.net/hotelImages/52027642/-1/27fe3403acf7a1fcf2a73d265accb016.jpg?ce=0&s=1024x768",
      "https://pix8.agoda.net/hotelImages/52027642/0/87cb8adc4945aae6a718170b00aaab6a.jpg?ce=0&s=1024x768"
    ]
  },
  {
    "hotel_id": "734770",
    "hotel_url": "https://www.agoda.com/airport-hotel-busan/hotel/busan-kr.html",
    "name": "Airport Hotel Busan",
    "detail": "The location of Airport hotel is near the Busan Gimhae airport about 5 minutes’ drive and the metro system purple line about 3 minutes’ walk. It also provides a convenient shuttle bus (which is a comfortable 8-seated minibus) from the hotel to the airport. The room is quite large and equipped with Jacuzzi. The soundproof of the room is excellent although near the airport. Its bed is very soft and comfortable. I fell asleep immediately after lying on the bed. However, I overslept in the morning and almost missed the scheduled time of the shuttle bus to the airport. The staff called me and reminded me kindly. They still carried me to the airport. I arrived there timely and did not miss the scheduled flight. Thanks so much! An exciting but good experience of my last day in Busan.",
    "area": "Gangseo-gu,Busan - View on map",
    "rating": "8",
    "reviews": "3466 reviews",
    "price": "96",
    "gallery": [
      "https://pix8.agoda.net/hotelImages/734770/-1/8b61a6e5a0a30521f067863e223651de.jpg?ca=7&ce=1&s=1024x768",
      "https://pix8.agoda.net/property/18528737/489836491/2c76f86f0b899df09fe1492d7c5bc559.jpg?ca=27&ce=0&s=1024x768",
      "https://pix8.agoda.net/hotelImages/734770/-1/722ae414311e160462e0cda03e81b1c3.jpg?ca=7&ce=1&s=1024x768",
      "https://pix8.agoda.net/hotelImages/734770/-1/0bb7356ebf8dbf6831567dd4672d7129.jpg?ca=7&ce=1&s=1024x768",
      "https://pix8.agoda.net/hotelImages/734770/-1/e34a1241bba61813201d1bc518fb2edd.jpg?ca=7&ce=1&s=1024x768",
      "https://pix8.agoda.net/hotelImages/734770/-1/35324d7dbb4291ae04590d2a128c305b.jpg?ca=9&ce=1&s=1024x768",
      "https://q-xx.bstatic.com/xdata/images/hotel/max1000/234835683.jpg?k=ebbc58e3bddb3abab2b8fe4fe84c49b45be4b0a56276871a160c4b358ed146c9&s=1024x768",
      "https://pix8.agoda.net/property/18528737/263153925/40d8cf869e17d3e64f2fb13c5f4f4444.jpeg?ce=0&s=1024x768",
      "https://pix8.agoda.net/hotelImages/734770/-1/721b9d2a0847047b4c55940762f187c5.jpg?ca=9&ce=1&s=1024x768"
    ]
  },
  {
    "hotel_id": "2962286",
    "hotel_url": "https://www.agoda.com/gwanganli-hotel-1_2/hotel/busan-kr.html",
    "name": "Gwanganli Hotel 1",
    "detail": "This hotel is AMAZING!!! I fell in love with the pictures at first, but once I arrived there I was in AWE. It’s brand new, (only been one month since opening) so everything is white, clean and beautiful. I initially chose the standard capsule cause it was so cheap, but my friend and I upgraded to the deluxe oceanfront capsule which was not that substantial of a price difference. It was amazing waking up to the beach view in the morning! The rooms are not that expensive either, especially the capsule rooms. When you check in, the friendly staff politely prompts you to take off your shoes before entering, it’s a no shoe zone indoors. They provide you with an electronic room key that gives you access to the elevator and your locker, which upon opening receive a nice care hotel package of pajamas, towels, tissues, a mini razor, and a small water bottle. It’s very modern which is nice. What really sold me was the karaoke system that’s in the lobby cafe area, it’s free to use as a hotel guest. The owner is super friendly and cool, he owns a very well known karaoke bar chain that is located in several areas in South Korea apparently. That’s why the karaoke sound system is such nice quality. I absolutely loved singing to songs overlooking the beach! I anticipate the karaoke being a popular thing amongst hotel guests in the busier summer months. The decor of this hotel is exceptional. Full window oceanfront views, squeaky clean white floors, gorgeous modern interior design is only a minor detail of this beautiful hotel. I loved being able to look at the beach waves while eating breakfast in the hotel cafe. The Room Rates are very reasonable for the quality, grace, and luxury of Gwanganli Hotel 1. It felt like paradise staying here. This hotel stay is a must if you ever visit Gwanganli beach in Busan!!!",
    "area": "Gwangan,Busan - View on map",
    "rating": "8.9",
    "reviews": "3530 reviews",
    "price": "73",
    "gallery": [
      "https://pix8.agoda.net/hotelImages/2962286/-1/988d76ca7a1c630fb9458f0d472135e0.jpg?ca=12&ce=1&s=1024x768",
      "https://pix8.agoda.net/hotelImages/2962286/-1/19983948079a7dd002ebd873fb375c47.jpg?ca=6&ce=1&s=1024x768",
      "https://q-xx.bstatic.com/xdata/images/hotel/max1000/117339302.jpg?k=cafe09480cfc29272d206599c864892970ee7ef8b1b737505baafcb7e18511f2&s=1024x768",
      "https://pix8.agoda.net/hotelImages/2962286/-1/25ffd034a0abe632779ff2a38687cb6e.jpg?ca=6&ce=1&s=1024x768",
      "https://q-xx.bstatic.com/xdata/images/hotel/max1000/118741031.jpg?k=ffe4018b603e1679505a3f2dc2c78b8e0c83173167bdaef3864206612201e473&s=1024x768",
      "https://q-xx.bstatic.com/xdata/images/hotel/max1000/118741018.jpg?k=ea350e432ee0a485e5b27f6f22cf40e5338058960b6660a802a4731ac25bab6c&s=1024x768",
      "https://pix8.agoda.net/hotelImages/2962286/-1/aed7b0114d1ffbff7d167888ab50b49f.jpg?ca=6&ce=1&s=1024x768",
      "https://q-xx.bstatic.com/xdata/images/hotel/max1000/118732064.jpg?k=390ea680844d9a5e191b5bed84ffa2086c813dc724201376d745fa5120f4747d&s=1024x768",
      "https://pix8.agoda.net/hotelImages/2962286/-1/318ba13e410219e7637db9ebc0a7fbcc.png?ca=6&ce=1&s=1024x768"
    ]
  },
  {
    "hotel_id": "6543659",
    "hotel_url": "https://www.agoda.com/airsky-hotel/hotel/busan-kr.html",
    "name": "Airsky Hotel",
    "detail": "Good price. Better room condition than Biz hotel in Busan central area. Free breakfast also good. Free pick up and sending to Kimhea airport. Near by subway station, so easy to access center of Busan. Wonderful. ",
    "area": "Gangseo-gu,Busan - View on map",
    "rating": "8.8",
    "reviews": "3541 reviews",
    "price": "118",
    "gallery": [
      "https://pix8.agoda.net/hotelImages/654/6543659/6543659_19020410150071989650.jpg?ca=7&ce=1&s=1024x768",
      "https://pix8.agoda.net/hotelImages/654/6543659/6543659_19082614150080007271.png?ca=9&ce=1&s=1024x768",
      "https://q-xx.bstatic.com/xdata/images/hotel/max1000/182419949.jpg?k=b75117d3671c39d783433f437533993afdaa71d4dd2d2f2f67db9cd10bcabbc3&s=1024x768",
      "https://q-xx.bstatic.com/xdata/images/hotel/max1000/284072512.jpg?k=044ab73edd9fe90eecf27bd09593762451b5f3538aa15087e1e21c5956d3ed44&s=1024x768",
      "https://pix8.agoda.net/hotelImages/654/6543659/6543659_19020410150071989646.jpg?ca=7&ce=1&s=1024x768",
      "https://q-xx.bstatic.com/xdata/images/hotel/max1000/182419988.jpg?k=79e027cfd6d14c8f0856aa5230cb8c09da97a2213cfaa9d2a1d492103c295336&s=1024x768",
      "https://pix8.agoda.net/property/69693301/0/1394f28682cbe86a0137ec2c02b7b05d.jpeg?ce=2&s=1024x768",
      "https://pix8.agoda.net/hotelImages/654/6543659/6543659_19020410150071989628.jpg?ca=7&ce=1&s=1024x768",
      "https://pix8.agoda.net/hotelImages/654/6543659/6543659_19020410150071989648.jpg?ca=7&ce=1&s=1024x768"
    ]
  },
  {
    "hotel_id": "4592179",
    "hotel_url": "https://www.agoda.com/toyoko-inn-busan-haeundae-2_6/hotel/busan-kr.html",
    "name": "Toyoko Inn Busan Haeundae 2",
    "detail": "I extremly like this hotel because of its cleanest, and warm. the staff's very helpful, the location is the best. Thank you for every thing, I enjoy it much. Love from Vietnam. ",
    "area": "Haeundae-gu,Busan - View on map",
    "rating": "8.7",
    "reviews": "6687 reviews",
    "price": "85",
    "gallery": [
      "https://pix8.agoda.net/hotelImages/459/4592179/4592179_18022816210062450269.jpg?ca=6&ce=1&s=1024x768",
      "https://pix8.agoda.net/property/77005684/0/aceccedc560434120b9a186eeaad6326.jpeg?ce=2&s=1024x768",
      "https://pix8.agoda.net/property/77005684/0/da34ef0690b392db23d8534726f2a0e6.jpeg?ce=2&s=1024x768",
      "https://pix8.agoda.net/property/77005684/0/e8679543fcc768702eae59bc51afb796.jpeg?ce=2&s=1024x768",
      "https://q-xx.bstatic.com/xdata/images/hotel/max1000/416265405.jpg?k=ce7a78a9cba95ad8a96372a8950d8c1426da5f240d730930be72617816497f40&s=1024x768",
      "https://pix8.agoda.net/property/108254/0/0bdf4c9bbe8cc636096190c06d7e12ac.jpeg?ce=2&s=1024x768",
      "https://pix8.agoda.net/property/77005684/0/1180ba7ca37b3382d5af0023f269f545.jpeg?ce=2&s=1024x768",
      "https://q-xx.bstatic.com/xdata/images/hotel/max1000/85392476.jpg?k=2a30d63b341dafe32d8b694e610fb5bd477209b184b9aeaed6310de78b1d21e6&s=1024x768",
      "https://pix8.agoda.net/property/77005684/0/8ddc1974aca1d5a309e8a1792aea9ff5.jpeg?ce=2&s=1024x768"
    ]
  },
  {
    "hotel_id": "56391618",
    "hotel_url": "https://www.agoda.com/marysol-by-haeundaebeach/hotel/busan-kr.html",
    "name": "Marysol by Haeundae Beach",
    "detail": "Room ocean view, perfect, loved the position and everything",
    "area": "Haeundae-gu,Busan - View on map",
    "rating": "8.4",
    "reviews": "1339 reviews",
    "price": "138",
    "gallery": [
      "https://pix8.agoda.net/hotelImages/56391618/0/818594fe9beee1532c731fdc55e8e352.png?ce=2&s=1024x768",
      "https://pix8.agoda.net/hotelImages/56391618/1207260973/7820791d5ac3515d08be5386071b6aba.jpg?ce=2&s=1024x768",
      "https://pix8.agoda.net/property/68646937/0/70a78aad30205f8483b61c5bd5a158c5.jpeg?ce=2&s=1024x768",
      "https://q-xx.bstatic.com/xdata/images/hotel/max1000/724130517.jpg?k=94cf2e8bdcc4043adcbe2b0127b2a92e45b17cf415b4a8cc217f0702a26aebc0&s=1024x768",
      "https://pix8.agoda.net/hotelImages/56391618/0/8bf519a2f9d2b915824ccf3a1c23d403.jpg?ce=2&s=1024x768",
      "https://q-xx.bstatic.com/xdata/images/hotel/max1000/721990869.jpg?k=87bdd4b1dde25d699617c716ae983bb8f7872c56fb2ebcbaa0806f29a1f17764&s=1024x768",
      "https://pix8.agoda.net/hotelImages/56391618/0/b82c18322f70c48d019449b40421104b.jpg?ce=2&s=1024x768",
      "https://pix8.agoda.net/hotelImages/56391618/-1/205353ebe66acb25d8d6276eb3add125.jpg?ce=0&s=1024x768",
      "https://pix8.agoda.net/property/68646937/0/77943891238e986e5683ff290ae2d067.jpeg?ce=2&s=1024x768"
    ]
  },
  {
    "hotel_id": "59456426",
    "hotel_url": "https://www.agoda.com/elmomento-songdo-residencs/hotel/busan-kr.html",
    "name": "Elmomento Songdo Residence",
    "detail": "Exceptional property with a gorgeous view from the property.",
    "area": "Seo-gu,Busan - View on map",
    "rating": "8.8",
    "reviews": "1812 reviews",
    "price": "83",
    "gallery": [
      "https://pix8.agoda.net/hotelImages/59456426/0/41d37bbe0b0e4fef0f2d99a6f25c705c.jpg?ce=0&s=1024x768",
      "https://q-xx.bstatic.com/xdata/images/hotel/max1000/597727296.jpg?k=912d8939cd5b3aeca83b0a987da5d44e82439f67af95114a0c8a92c67d1185fe&s=1024x768",
      "https://q-xx.bstatic.com/xdata/images/hotel/max1000/589703348.jpg?k=67b2da88f8b72835b884c92ecafe9dde88017a5aa30d3639378cbef585b3ca89&s=1024x768",
      "https://pix8.agoda.net/hotelImages/59456426/-1/f6ae40561b87f5c0aa9f377898f62751.jpg?ce=0&s=1024x768",
      "https://pix8.agoda.net/hotelImages/59456426/895906259/795475f075cec04ece2f70c727ac7b66.jpg?ce=0&s=1024x768",
      "https://q-xx.bstatic.com/xdata/images/hotel/max1000/751684116.jpg?k=ab08d96103581b619194cafc13cec598ade959591a41bd4f3ac9e6660deb1618&s=1024x768",
      "https://q-xx.bstatic.com/xdata/images/hotel/max1000/589703355.jpg?k=de38f3550cf3d7000a809f8b930787ef4d7d91a3d4b345240774d7b334d9f0ae&s=1024x768",
      "https://q-xx.bstatic.com/xdata/images/hotel/max1000/582995877.jpg?k=0ccfccdea88bdf43fe47eb355adf927966554c96185b69b655870c8740735586&s=1024x768",
      "https://q-xx.bstatic.com/xdata/images/hotel/max1000/589704053.jpg?k=ea2d6771b41ba0bb802a837ff4aa07e995243bdae93b36ec931a9c4f613820bc&s=1024x768"
    ]
  },
  {
    "hotel_id": "42958",
    "hotel_url": "https://www.agoda.com/lotte-hotel-busan/hotel/busan-kr.html",
    "name": "Lotte Hotel Busan",
    "detail": "Busan is very clean town and after eating everyone have to clear there own cutlery. We stay at Lotte Busan hotel, taxi is not expensive but if you prefer walking nearby a lot of restaurant and coffee cafe street. Train station also easier with a lot of shopping near station. Attractions a lot of walking and climbing up stairs. I when with my two sisters, we enjoy the 7 days trips.",
    "area": "Seo-myeon,Busan - View on map",
    "rating": "9",
    "reviews": "11714 reviews",
    "price": "228",
    "gallery": [
      "https://pix8.agoda.net/hotelImages/42958/-1/4591e6c1349743676fb0fe79cff45771.jpg?ce=0&s=1024x768",
      "https://pix8.agoda.net/hotelImages/25140939/1153966142/09d3319ee6ad29c2b9b52e131a548c12.jpeg?ce=2&s=1024x768",
      "https://q-xx.bstatic.com/xdata/images/hotel/max1000/460821055.jpg?k=7811ff7badaf933d171e0324edf1fec98cf4c587397aeb1ff243b9839aa1c5d0&s=1024x768",
      "https://pix8.agoda.net/hotelImages/429/42958/42958_16112909110049179710.jpg?ca=6&ce=1&s=1024x768",
      "https://pix8.agoda.net/hotelImages/42958/-1/9d8412fba4b345e668c2cbc03a094662.jpg?ce=0&s=1024x768",
      "https://q-xx.bstatic.com/xdata/images/hotel/max1000/449523582.jpg?k=880c6b4b7cbc1961864a8c1ac2ba11f86d1d326a038044f6e053f035061af469&s=1024x768",
      "https://q-xx.bstatic.com/xdata/images/hotel/max1000/308725186.jpg?k=8f5e532de3a50048b4df828b23c892f4034db30e3c535c8862b846d0791d4ca4&s=1024x768",
      "https://q-xx.bstatic.com/xdata/images/hotel/max1000/38633775.jpg?k=ff8defedbca44fce36727b238f8150c49ac60e054d9560358926ab45c6b7f87c&s=1024x768",
      "https://q-xx.bstatic.com/xdata/images/hotel/max1000/203942987.jpg?k=d21a8e93f3a769c49d52aeeb2f1f51b902614e922fa36f73e2ffa817b0109085&s=1024x768"
    ]
  },
  {
    "hotel_id": "4576021",
    "hotel_url": "https://www.agoda.com/toyoko-inn-busan-station-1_8/hotel/busan-kr.html",
    "name": "Toyoko Inn Busan Station 1",
    "detail": "The location is superb, just across the road from Busan KTX Exit 1 where there are small eateries and 24 hrs convenience stores. At Level 1 of the hotel lobby, there are 2 washers & dryers (beside the toilets) which is a plus factor and there is drinks vending machine, water dispenser, ice dispenser and microwave. The 2 of us stayed in the twin bedroom at 20th floor for 3 nights. The hotel room and bathroom is small and we can only open our L-sized luggage on the bed, but everything we need is there and the room is clean. But when we want to request for additional pillows, we can only ask for maximum 1 extra pillow per room. And when we have some issues with the washer & dryer, we tried to approach the counter staff for help but they cannot offer any help or assistance at all, which is pretty disappointing. Overall, the experience is good, room is clean, really easy to reach both Busan KTX and Busan Station Line 1 metro subway (Tips: There's a lift in between exit 4 and 6 if you are too tired from climbing stairs). Staff needs to improve on service standard as they were pretty cold and nonchalant attitude towards us.",
    "area": "Dong-gu,Busan - View on map",
    "rating": "8.8",
    "reviews": "9422 reviews",
    "price": "56",
    "gallery": [
      "https://pix8.agoda.net/hotelImages/4576021/-1/541a573f49867bafa93fa5840b6c1e6c.jpg?ce=0&s=1024x768",
      "https://q-xx.bstatic.com/xdata/images/hotel/max1000/652260120.jpg?k=df069827024f9c8e53e9c2cd61107879bafb56de75985a9f0d90191f1329054f&s=1024x768",
      "https://pix8.agoda.net/hotelImages/4576021/-1/c9a6bb54cd76f3f141ce96af4b7c3eb1.jpg?ce=0&s=1024x768",
      "https://q-xx.bstatic.com/xdata/images/hotel/max1000/706326909.jpg?k=215d0c5704d69c475ca33ea2e1bd8705cc778003d1642a03d81c4e71a3b2cadd&s=1024x768",
      "https://pix8.agoda.net/property/77003740/0/2f365e95175d7672b62481e5db54af49.jpeg?ce=2&s=1024x768",
      "https://pix8.agoda.net/hotelImages/4576021/0/92405d3678d922dd7ad1b5142e8c5d36.png?ce=2&s=1024x768",
      "https://pix8.agoda.net/property/4576021/0/004638db5a23fe98bc8de77bc1a8c4b2.jpeg?ce=2&s=1024x768",
      "https://q-xx.bstatic.com/xdata/images/hotel/max1000/476545597.jpg?k=77e9a0e61fc8941a59e76aa0ee67cc8ac12037d39465bc1ac19e1aea23934bca&s=1024x768",
      "https://pix8.agoda.net/property/4576021/0/f38c5828b335219982364547ac80c339.jpeg?ce=2&s=1024x768"
    ]
  },
  {
    "hotel_id": "2205026",
    "hotel_url": "https://www.agoda.com/ramada-encore-by-wyndham-busan-haeundae/hotel/busan-kr.html",
    "name": "Ramada Encore by Wyndham Busan Haeundae",
    "detail": "Stayed here for a night on our 3 day trip to Busan. This was probably the best accommodation we had during our South Korean trip. Will definitely recommend this to anyone considering.",
    "area": "Haeundae-gu,Busan - View on map",
    "rating": "8.7",
    "reviews": "14543 reviews",
    "price": "101",
    "gallery": [
      "https://pix8.agoda.net/hotelImages/2205026/0/c22d36b5baa9e61a3e47730838c7e61b.jpg?ca=0&ce=1&s=1024x768",
      "https://q-xx.bstatic.com/xdata/images/hotel/max1000/234469620.jpg?k=d92e05790c46c5ad60dd8e8c5e8bc2c1286ccd6db2b3fa972e34743d060746fd&s=1024x768",
      "https://q-xx.bstatic.com/xdata/images/hotel/max1000/109910755.jpg?k=c2d0d616e93c2e91693c9c54fe1ff20b967e00b988c25c2b2dcca368e34f1c9f&s=1024x768",
      "https://q-xx.bstatic.com/xdata/images/hotel/max1000/193815975.jpg?k=872b9dd53716ab35666fac256e91f2ac5dacfef7f3b8b719f9ca2989190b5bce&s=1024x768",
      "https://q-xx.bstatic.com/xdata/images/hotel/max1000/238673051.jpg?k=160df14581129948eb4b3430269dfb2237b2c9b7c3824020c3600bfa58af3f13&s=1024x768",
      "https://q-xx.bstatic.com/xdata/images/hotel/max1000/234469700.jpg?k=65dd0032acf83b14d86dee48fbb69a8a742a72c943154ed17d929182db49c78c&s=1024x768",
      "https://q-xx.bstatic.com/xdata/images/hotel/max1000/109904235.jpg?k=3324a05aa56ee60e04655277eb4b63f4da546256eb1c69e040fea2496738e0e9&s=1024x768",
      "https://q-xx.bstatic.com/xdata/images/hotel/max1000/109898956.jpg?k=73a36439817a34361cf257dc8efe4ad9cf309722910fbae5eac9d6ac0150d7d0&s=1024x768",
      "https://pix8.agoda.net/hotelImages/2205026/-1/3edb998e0d2a3091c709ea21c83caa6f.jpg?ca=17&ce=1&s=1024x768"
    ]
  }
]